image_processing_DIO_JoelPB/__init__.py
image_processing_DIO_JoelPB/processing/__init__.py
image_processing_DIO_JoelPB/processing/combination.py
image_processing_DIO_JoelPB/processing/transformation.py
image_processing_DIO_JoelPB/utils/__init__.py
image_processing_DIO_JoelPB/utils/io.py
image_processing_DIO_JoelPB/utils/plot.py
image_processing_DIO_JoelPB-0.0.1.dist-info/METADATA
image_processing_DIO_JoelPB-0.0.1.dist-info/WHEEL
image_processing_DIO_JoelPB-0.0.1.dist-info/top_level.txt
image_processing_DIO_JoelPB-0.0.1.dist-info/RECORD
