Metadata-Version: 2.1
Name: image_processing_DIO_JoelPB
Version: 0.0.1
Summary: Pacote para o projeto da DIO
Home-page: https://github.com/JoelPB/image-processing-package-DIO.git
Author: Joel de Oliveira
Author-email: coffee.program.joel@gmail.com
License: MIT
Requires-Python: >=3.8
Requires-Dist: matplotlib
Requires-Dist: numpy
Requires-Dist: scikit-image >=0.16.1
